{"notices":[{"id":"a2z7fd","stamp":"2024-02-23T21:19:50.90694661Z","notice":{"body":"Started managing this issue as Gov4Git concern `23` with initial __priority score__ of `0.000000`.\n\nThis project is managed by [Gov4Git](https://gov4git.org), a decentralized governance system for collaborative git projects.\nTo participate in governance, __install the [Gov4Git desktop app](https://github.com/gov4git/desktop-application)__.\n\t"},"shown":true},{"id":"mxb6su","stamp":"2024-02-23T21:19:50.911648113Z","notice":{"body":"This issue's __priority score__ is now `0.000000`.\nThe __cost of priority__ is `0.000000`.\nThe __projected bounty__ is now `0.000000`."},"shown":true},{"id":"penpu3","stamp":"2024-02-23T21:19:50.911649977Z","notice":{"body":"The set of eligible proposals claiming this issue is empty.\n"},"shown":true},{"id":"4sbwcu","stamp":"2024-02-26T15:13:15.626545937Z","notice":{"body":"This issue's __priority score__ is now `3.000000`.\nThe __cost of priority__ is `9.000000`.\nThe __projected bounty__ is now `9.000000`."},"shown":true},{"id":"vmrhro","stamp":"2024-02-26T15:13:15.626547691Z","notice":{"body":"The set of eligible proposals claiming this issue is empty.\n"},"shown":true},{"id":"cbazuw","stamp":"2024-04-05T20:38:33.56315117Z","notice":{"body":"This issue, managed as Gov4Git proposal `23`, has been cancelled 🌂\n\nThe issue priority tally was `3.000000`.\n\nRefunds issued:\n- User @ctessum was refunded `9.000000` credits\n\nTally breakdown by user:\n- User @ctessum contributed `3.000000` votes\n"},"shown":true}]}
